LICENSE
MANIFEST.in
README.md
setup.cfg
setup.py
samwise/__init__.py
samwise/__main__.py
samwise/constants.py
samwise/exceptions.py
samwise.egg-info/PKG-INFO
samwise.egg-info/SOURCES.txt
samwise.egg-info/dependency_links.txt
samwise.egg-info/entry_points.txt
samwise.egg-info/not-zip-safe
samwise.egg-info/requires.txt
samwise.egg-info/top_level.txt
samwise/features/__init__.py
samwise/features/package.py
samwise/features/template.py
samwise/utils/__init__.py
samwise/utils/aws.py
samwise/utils/cli.py
samwise/utils/filesystem.py
samwise/utils/formatters.py
samwise/utils/standards.py
samwise/utils/tools.py
samwise/utils/zip.py