Metadata-Version: 1.1
Name: samwise
Version: 0.1.3
Summary: SAMWise is a tool for packaging and deploying AWS Serverless Application Model applications
Home-page: https://github.com/Cloudzero/samwise
Author: CloudZero
Author-email: support@cloudzero.com
License: MIT
Keywords: SAM AWS CloudZero Serverless
Platform: MacOS
Platform: Unix
Classifier: Development Status :: 4 - Beta
Classifier: Intended Audience :: Developers
Classifier: Natural Language :: English
Classifier: Programming Language :: Python :: 3.8
Classifier: License :: OSI Approved :: MIT License
Classifier: Operating System :: MacOS
Classifier: Operating System :: Unix
